<?xml version="1.0" ?>
<annotation>
	<filename>6.jpg</filename>
	<size>
		<width>4096</width>
		<height>3072</height>
		<depth>3</depth>
	</size>
	<object>
		<name>Figure</name>
		<pose>Unspecified</pose>
		<truncated>0</truncated>
		<difficult>0</difficult>
		<bndbox>
			<xmin>2295</xmin>
			<ymin>699</ymin>
			<xmax>3174</xmax>
			<ymax>1874</ymax>
		</bndbox>
	</object>
	<object>
		<name>Figure</name>
		<pose>Unspecified</pose>
		<truncated>0</truncated>
		<difficult>0</difficult>
		<bndbox>
			<xmin>644</xmin>
			<ymin>412</ymin>
			<xmax>1639</xmax>
			<ymax>1966</ymax>
		</bndbox>
	</object>
	<object>
		<name>Title</name>
		<pose>Unspecified</pose>
		<truncated>0</truncated>
		<difficult>0</difficult>
		<bndbox>
			<xmin>3531</xmin>
			<ymin>1903</ymin>
			<xmax>4077</xmax>
			<ymax>2805</ymax>
		</bndbox>
	</object>
	<object>
		<name>Title</name>
		<pose>Unspecified</pose>
		<truncated>0</truncated>
		<difficult>0</difficult>
		<bndbox>
			<xmin>529</xmin>
			<ymin>2582</ymin>
			<xmax>1920</xmax>
			<ymax>2829</ymax>
		</bndbox>
	</object>
	<object>
		<name>Text</name>
		<pose>Unspecified</pose>
		<truncated>0</truncated>
		<difficult>0</difficult>
		<bndbox>
			<xmin>169</xmin>
			<ymin>2833</ymin>
			<xmax>2310</xmax>
			<ymax>3071</ymax>
		</bndbox>
	</object>
	<object>
		<name>Title</name>
		<pose>Unspecified</pose>
		<truncated>0</truncated>
		<difficult>0</difficult>
		<bndbox>
			<xmin>12</xmin>
			<ymin>457</ymin>
			<xmax>523</xmax>
			<ymax>3028</ymax>
		</bndbox>
	</object>
	<object>
		<name>Title</name>
		<pose>Unspecified</pose>
		<truncated>0</truncated>
		<difficult>0</difficult>
		<bndbox>
			<xmin>23</xmin>
			<ymin>1065</ymin>
			<xmax>413</xmax>
			<ymax>2874</ymax>
		</bndbox>
	</object>
	<object>
		<name>Figure</name>
		<pose>Unspecified</pose>
		<truncated>0</truncated>
		<difficult>0</difficult>
		<bndbox>
			<xmin>3506</xmin>
			<ymin>2794</ymin>
			<xmax>4094</xmax>
			<ymax>3070</ymax>
		</bndbox>
	</object>
</annotation>
